rtl/defines.v
//***********************
//全局宏定义
//***********************
`define CPU_CLOCK_HZ        10000000        //cpu时钟10MHz
`define CPU_RESET_ADDR      32'h00000000    //cpu复位地址
`define RST_ENABLE          1'b0            //复位有效
`define RST_DISABLE         1'b1            //复位无效
`define ZERO_WORD           32'h00000000    //32位的数值0
`define WRITE_ENABLE        1'b1            //写使能
`define WRITE_DISABLE       1'b0            //写禁止
`define READ_ENABLE         1'b1            //读使能
`define READ_DISABLE        1'b0            //读禁止
`define EXCP_SYNC_ASSERT    2'b01           //同步异常
`define EXCP_ASYNC_ASSERT_1   2'b10           //异步异常1
`define EXCP_ASYNC_ASSERT_2   2'b11           //异步异常2

//***********************
//IDU信息总线宏定义
//***********************

`define DEC_INST_OP_WIDTH       4                           //DEC指令类型信息宽度
`define DEC_INST_OP             `DEC_INST_OP_WIDTH-1:0      //DEC指令类型信息

//R instruction decode bus
`define DEC_INST_R              `DEC_INST_OP_WIDTH'd1      //R型指令
`define DEC_INST_R_ADD          `DEC_INST_OP_WIDTH         //ADD指令
`define DEC_INST_R_SUB          `DEC_INST_R_ADD+1          
`define DEC_INST_R_SLL          `DEC_INST_R_SUB+1 
`define DEC_INST_R_SLT          `DEC_INST_R_SLL+1 
`define DEC_INST_R_SLTU         `DEC_INST_R_SLT+1 
`define DEC_INST_R_XOR          `DEC_INST_R_SLTU+1
`define DEC_INST_R_SRL          `DEC_INST_R_XOR+1
`define DEC_INST_R_SRA          `DEC_INST_R_SRL+1
`define DEC_INST_R_OR           `DEC_INST_R_SRA+1
`define DEC_INST_R_AND          `DEC_INST_R_OR+1     

`define DEC_R_INFO_BUS_WIDTH    `DEC_INST_R_AND+1           //R型指令译码信息宽度
`define DEC_R_INFO_BUS          `DEC_R_INFO_BUS_WIDTH-1:0   //R型指令译码信息

//I instruction decode bus
`define DEC_INST_I              `DEC_INST_OP_WIDTH'd2      //I型指令
`define DEC_INST_I_ADDI         `DEC_INST_OP_WIDTH         //ADDI指令
`define DEC_INST_I_SLTI         `DEC_INST_I_ADDI+1 
`define DEC_INST_I_SLTIU        `DEC_INST_I_SLTI+1 
`define DEC_INST_I_XORI         `DEC_INST_I_SLTIU+1
`define DEC_INST_I_ORI          `DEC_INST_I_XORI+1
`define DEC_INST_I_ANDI         `DEC_INST_I_ORI+1 
`define DEC_INST_I_SLLI         `DEC_INST_I_ANDI+1  
`define DEC_INST_I_SRLI         `DEC_INST_I_SLLI+1
`define DEC_INST_I_SRAI         `DEC_INST_I_SRLI+1

`define DEC_I_INFO_BUS_WIDTH    `DEC_INST_I_SRAI+1          //I型指令译码信息宽度
`define DEC_I_INFO_BUS          `DEC_I_INFO_BUS_WIDTH-1:0   //I型指令译码信息

//U instruction decode bus
`define DEC_INST_U              `DEC_INST_OP_WIDTH'd3      //U型指令
`define DEC_INST_U_LUI          `DEC_INST_OP_WIDTH         //LUI指令
`define DEC_INST_U_AUIPC        `DEC_INST_U_LUI+1 

`define DEC_U_INFO_BUS_WIDTH    `DEC_INST_U_AUIPC+1         //U型指令译码信息宽度
`define DEC_U_INFO_BUS          `DEC_U_INFO_BUS_WIDTH-1:0   //U型指令译码信息

//L(OAD) instruction decode bus
`define DEC_INST_L              `DEC_INST_OP_WIDTH'd4      //L型指令
`define DEC_INST_L_LB           `DEC_INST_OP_WIDTH         //LB指令
`define DEC_INST_L_LH           `DEC_INST_L_LB+1 
`define DEC_INST_L_LW           `DEC_INST_L_LH+1
`define DEC_INST_L_LBU          `DEC_INST_L_LW+1 
`define DEC_INST_L_LHU          `DEC_INST_L_LBU+1 

`define DEC_L_INFO_BUS_WIDTH    `DEC_INST_L_LHU+1           //L型指令译码信息宽度
`define DEC_L_INFO_BUS          `DEC_L_INFO_BUS_WIDTH-1:0   //L型指令译码信息

//S(TORE) instruction decode bus
`define DEC_INST_S              `DEC_INST_OP_WIDTH'd5      //S型指令
`define DEC_INST_S_SB           `DEC_INST_OP_WIDTH         //SB指令
`define DEC_INST_S_SH           `DEC_INST_S_SB+1 
`define DEC_INST_S_SW           `DEC_INST_S_SH+1

`define DEC_S_INFO_BUS_WIDTH    `DEC_INST_S_SW+1           //S型指令译码信息宽度
`define DEC_S_INFO_BUS          `DEC_S_INFO_BUS_WIDTH-1:0  //S型指令译码信息

//J(UMP) instruction decode bus
`define DEC_INST_J              `DEC_INST_OP_WIDTH'd6      //J型指令
`define DEC_INST_J_JAL          `DEC_INST_OP_WIDTH         //JAL指令
`define DEC_INST_J_JALR         `DEC_INST_J_JAL+1 

`define DEC_J_INFO_BUS_WIDTH    `DEC_INST_J_JALR+1         //J型指令译码信息宽度
`define DEC_J_INFO_BUS          `DEC_J_INFO_BUS_WIDTH-1:0  //J型指令译码信息

//CONTROL STATE REGISTER instruction decode bus
`define DEC_INST_CSR            `DEC_INST_OP_WIDTH'd7       //CSR型指令
`define DEC_INST_CSR_CSRRW      `DEC_INST_OP_WIDTH
`define DEC_INST_CSR_CSRRS      `DEC_INST_CSR_CSRRW+1    
`define DEC_INST_CSR_CSRRC      `DEC_INST_CSR_CSRRS+1
`define DEC_INST_CSR_CSRRWI     `DEC_INST_CSR_CSRRC+1
`define DEC_INST_CSR_CSRRSI     `DEC_INST_CSR_CSRRWI+1
`define DEC_INST_CSR_CSRRCI     `DEC_INST_CSR_CSRRSI+1

`define DEC_CSR_INFO_BUS_WIDTH  `DEC_INST_CSR_CSRRCI+1      //CSR型指令译码信息宽度
`define DEC_CSR_INFO_BUS        `DEC_CSR_INFO_BUS_WIDTH-1:0 //CSR型指令译码信息

//MUL and DIV instruction
`define DEC_INST_MD             `DEC_INST_OP_WIDTH'd8       //MD型指令
`define DEC_INST_MD_MUL         `DEC_INST_OP_WIDTH
`define DEC_INST_MD_MULH        `DEC_INST_MD_MUL+1
`define DEC_INST_MD_MULHSU      `DEC_INST_MD_MULH+1
`define DEC_INST_MD_MULHU       `DEC_INST_MD_MULHSU+1
`define DEC_INST_MD_DIV         `DEC_INST_MD_MULHU+1
`define DEC_INST_MD_DIVU        `DEC_INST_MD_DIV+1
`define DEC_INST_MD_REM         `DEC_INST_MD_DIVU+1
`define DEC_INST_MD_REMU        `DEC_INST_MD_REM+1

`define DEC_MD_INFO_BUS_WIDTH   `DEC_INST_MD_REMU+1        //MD型指令译码信息宽度
`define DEC_MD_INFO_BUS         `DEC_MD_INFO_BUS_WIDTH-1:0 //MD型指令译码信息

//dec info bus
`define DEC_INFO_BUS_WIDTH      `DEC_R_INFO_BUS_WIDTH       //选取最长宽度为DEC信息总线宽度
`define DEC_INFO_BUS            `DEC_INFO_BUS_WIDTH-1:0     //DEC信息总线

//SYSTEM instruction info bus
`define DEC_SYS_BUS_WIDTH       3                           //特权(系统)指令信息总线宽度
`define DEC_SYS_BUS             `DEC_SYS_BUS_WIDTH-1:0      //特权(系统)指令信息总线

`define DEC_SYS_INST_ECALL      0                           //ecall指令
`define DEC_SYS_INST_EBREAK     `DEC_SYS_INST_ECALL+1
`define DEC_SYS_INST_MRET       `DEC_SYS_INST_EBREAK+1

//***********************
//EXE信息总线宏定义
//***********************
`define EXE_INST_OP_WIDTH       2                           //EXE指令类型信息宽度
`define EXE_INST_OP             `EXE_INST_OP_WIDTH-1:0      //EXE指令类型信息

`define EXE_INST_L              `EXE_INST_OP_WIDTH'd1       //L型指令
`define EXE_INST_L_LB           `EXE_INST_OP_WIDTH          //LB指令
`define EXE_INST_L_LH           `EXE_INST_L_LB+1 
`define EXE_INST_L_LW           `EXE_INST_L_LH+1
`define EXE_INST_L_LBU          `EXE_INST_L_LW+1 
`define EXE_INST_L_LHU          `EXE_INST_L_LBU+1 

`define EXE_L_INFO_BUS_WIDTH    `EXE_INST_L_LHU+1           //S型指令信息宽度
`define EXE_L_INFO_BUS          `EXE_L_INFO_BUS_WIDTH-1:0   //S型指令信息

`define EXE_INST_S              `EXE_INST_OP_WIDTH'd2       //S型指令
`define EXE_INST_S_SB           `EXE_INST_OP_WIDTH          //SB指令
`define EXE_INST_S_SH           `EXE_INST_S_SB+1 
`define EXE_INST_S_SW           `EXE_INST_S_SH+1

`define EXE_S_INFO_BUS_WIDTH    `EXE_INST_S_SW+1           //S型指令信息宽度
`define EXE_S_INFO_BUS          `EXE_S_INFO_BUS_WIDTH-1:0   //S型指令信息

`define EXE_INFO_BUS_WIDTH      `EXE_L_INFO_BUS_WIDTH       //选取最长宽度为EXE信息总线宽度
`define EXE_INFO_BUS            `EXE_INFO_BUS_WIDTH-1:0     //EXE信息总线
//***********************
//具体指令的宏定义
//***********************

//***********************
//指令存储器ROM宏定义
//***********************
`define ROM_DEPTH           8192            //指令存储器的深度，单位为word(4字节)
//***********************
//数据存储器ROM宏定义
//***********************
`define MEM_DATA_BUS_WIDTH  `REG_BUS_WIDTH          //数据存储器数据总线宽度
`define MEM_DATA_BUS        `REG_BUS                //数据存储器数据总线
`define MEM_ADDR_BUS_WIDTH  `REG_BUS_WIDTH          //数据存储器地址总线宽度
`define MEM_ADDR_BUS        `MEM_ADDR_BUS_WIDTH-1:0 //数据存储器地址总线
`define RAM_DEPTH           4096                    //数据存储器的深度，单位为word(4字节)

//***********************
//通用寄存器宏定义
//***********************
`define REG_BUS_WIDTH        32                      //regfile数据总线宽度
`define REG_BUS              `REG_BUS_WIDTH-1:0      //regfile数据总线
`define REG_ADDR_BUS_WIDTH   5                       //regfile地址总线宽度
`define REG_ADDR_BUS         `REG_ADDR_BUS_WIDTH-1:0 //regfile地址总线
`define REG_NUM              32                      //regfile数目
`define DOUBLE_REG_BUS_WIDTH 2*`REG_BUS_WIDTH
`define DOUBLE_REG_BUS       `DOUBLE_REG_BUS_WIDTH-1:0   
//***********************
//控制状态寄存器宏定义
//***********************
`define CSR_ADDR_BUS_WIDTH  12                      //csr地址总线宽度
`define CSR_ADDR_BUS        `CSR_ADDR_BUS_WIDTH-1:0 //csr地址总线
// CSR 地址
`define CSR_CYCLE   12'hc00
`define CSR_CYCLEH  12'hc80
`define CSR_MTVEC   12'h305
`define CSR_MCAUSE  12'h342
`define CSR_MEPC    12'h341
`define CSR_MIE     12'h304
`define CSR_MIP     12'h344
`define CSR_MSTATUS 12'h300
`define CSR_MSCRATCH 12'h340

rtl/perip/ahb_sram/sram_8kx8.v
/*
cen_i   wen_i   data_o      mode
 h       x      last_data   standby
 l       l      data_in     write
 l       h      sram_data   read
*/
module sram_8kx8 #(
   parameter		   DWIDTH = 8   ,
   parameter		   DEPTH = 8192 ,
   parameter		   AWIDTH = 13
) (
    input   wire                    clk     ,
    input   wire                    cen_i   ,
    input   wire                    wen_i   ,
    input   wire    [AWIDTH-1:0]    addr_i  ,
    input   wire    [DWIDTH-1:0]    data_i  ,
    output  wire    [DWIDTH-1:0]    data_o  
);

    reg [DWIDTH-1:0]    mem [0:DEPTH-1];


    always @(posedge clk) begin
        if (!cen_i) begin
            if (!wen_i) begin
                mem[addr_i] <= data_i;   
            end
        end
    end

    reg [DWIDTH-1:0]    data_r;
    always @(*) begin
        if (!cen_i) begin
            if (!wen_i) begin
                data_r <= data_i;   
            end else begin
                data_r <= mem[addr_i];
            end
        end
    end
    assign data_o = data_r;

//  assign data_o = !cen_i ? (!wen_i ? data_i : mem[addr_i]) : data_o;
//  若addr_i先到，cen_i后到，则会输出新数据，而不是保持原有数据。

endmodule  //sram_8kx8

rtl/perip/ahb_sram/ahb_sram.v
`include "../../core/defines.v"

module ahb_sram (
    input   wire                    hclk        ,
    input   wire                    sram_clk    ,
    input   wire    		        hresetn     ,
    
    input   wire    		        hsel_i      ,
    input   wire   	 	            hwrite_i    ,
    input   wire			        hready_i    ,
    input   wire    [2:0]  	        hsize_i     ,
    input   wire    [2:0]  	        hburst_i    ,
    input   wire    [1:0]  	        htrans_i    ,
    input   wire    [`HDATA_BUS] 	hwdata_i    ,
    input   wire    [`HADDR_BUS] 	haddr_i     ,	
    
    output  wire                    hreadyout_o ,
    output  wire    [1:0]           hresp_o     ,
    output  wire    [`HDATA_BUS]    hrdata_o    
);

    //HTRANS
    localparam HTRANS_IDLE = 2'b00;
  //localparam HTRANS_BUSY = 2'b00;
    localparam HTRANS_NONSEQ = 2'b10;
  //localparam HTRANS_SEQ = 2'b00;  

    //HBURSTS
    localparam HBURSTS_SINGLE = 3'b000;
  //localparam HBURSTS_INCR = 3'b001;
  //localparam HBURSTS_WRAP4 = 3'b010;
  //...... 

    reg                 hwrite_r    ;
    reg [2:0]           hsize_r     ;
    reg [2:0]           hburst_r    ;
    reg [1:0]           htrans_r    ;
    reg [`HADDR_BUS] 	haddr_r     ;

    always @(posedge hclk or negedge hresetn) begin
        if(!hresetn) begin
            hwrite_r <= 1'b0;
            hsize_r <= 3'b000;
            hburst_r <= 3'b000;
            htrans_r <= 2'b00;
            haddr_r <= `HADDR_BUS_WIDTH'h0;
        end else if (hsel_i && hready_i) begin
            hwrite_r <= hwrite_i;
            hsize_r <= hsize_i;
            hburst_r <= hburst_i; //一直为single
            htrans_r <= htrans_i;
            haddr_r <= haddr_i;
        end else begin
            hwrite_r <= 1'b0;
            hsize_r <= 3'b000;
            hburst_r <= 3'b000;
            htrans_r <= 2'b00;
            haddr_r <= `HADDR_BUS_WIDTH'h0;            
        end
    end

    assign hreadyout_o = 1'b1; //sram一直有效
    assign hresp_o = 2'b00; //ok

    wire    sram_cs = (hburst_r == HBURSTS_SINGLE) || (htrans_r == HTRANS_NONSEQ);
    wire    sram_read = sram_cs && !hwrite_r;
    wire    sram_write = sram_cs && hwrite_r;
    wire    sram_wen = !sram_write;

    wire    sram_bank_sel = haddr_r[15] ? 1'b1 : 1'b0; //sram_bank_sel = 1'b1 select bank1
    wire    [`HDATA_BUS]    sram_wdata = hwdata_i;

    wire    [`HDATA_BUS]    sram_bank0_rdata;
    wire    [`HDATA_BUS]    sram_bank1_rdata;
    wire    [`HDATA_BUS]    sram_rdata = sram_bank_sel ? sram_bank1_rdata : sram_bank0_rdata;

    assign hrdata_o = sram_rdata;

    wire    [12:0]  sram_addr = haddr_r[`HADDR_BUS_WIDTH-1:2]; //sram_addr=haddr/4

    reg [3:0]   bank_csn;
    always @(*) begin
        bank_csn = 4'b1111;
        case (hsize_r)
            3'b010: begin //32bit
                bank_csn = 4'b0000;
            end
            3'b001: begin //16bit
                if (haddr_r[1]) begin
                    bank_csn = 4'b0011;                    
                end else begin
                    bank_csn = 4'b1100;
                end
            end
            3'b000: begin //8bit
                case(haddr_r[1:0])
                    2'b00: begin
                        bank_csn = 4'b0001;
                    end
                    2'b01: begin
                        bank_csn = 4'b0010;
                    end
                    2'b10: begin
                        bank_csn = 4'b0100;
                    end
                    2'b11: begin
                        bank_csn = 4'b1000;
                    end
                endcase
            end
        endcase
    end

    wire    [3:0]   bank0_csn = (sram_cs && sram_bank_sel) ? bank_csn : 4'b1111;
    wire    [3:0]   bank1_csn = (sram_cs && !sram_bank_sel) ? bank_csn : 4'b1111;

    genvar i;
    for (i=0; i<4; i=i+1) begin: bank0
        sram_8kx8 u_sram_8kx8(
            .clk(sram_clk),
            .cen_i(bank0_csn[i]),
            .wen_i(sram_wen),
            .addr_i(sram_addr),
            .data_i(sram_wdata[i*8+:8]),
            .data_o(sram_bank0_rdata[i*8+:8])
        );
    end

    genvar j;
    for (j=0; j<4; j=j+1) begin: bank1
        sram_8kx8 u_sram_8kx8(
            .clk(sram_clk),
            .cen_i(bank1_csn[j]),
            .wen_i(sram_wen),
            .addr_i(sram_addr),
            .data_i(sram_wdata[j*8+:8]),
            .data_o(sram_bank1_rdata[j*8+:8])
        );
    end

endmodule //ahb_sram

rtl/perip/ahb_sram/ahb_sram_tb.v
module ahb_sram_tb ();
    reg                     hclk        ;
    reg                     sram_clk    ;
    reg    		            hresetn     ;
    
    reg    		            hsel_i      ;
    reg   	 	            hwrite_i    ;
    reg			            hready_i    ;
    reg    [2:0]  	        hsize_i     ;
    reg    [2:0]  	        hburst_i    ;
    reg    [1:0]  	        htrans_i    ;
    reg    [31:0] 	hwdata_i    ;
    reg    [31:0] 	haddr_i     ;	
    
    wire                    hreadyout_o ;
    wire    [1:0]           hresp_o     ;
    wire    [31:0]    hrdata_o    ; 

    always #10 hclk = ~hclk;
    always @ (*) sram_clk = ~hclk;

    initial begin
        hclk <= 1'b0;
        hresetn <= 1'b0;
        hsel_i <= 1'b0;
        hwrite_i <= 1'b0;
        hready_i <= hreadyout_o;
        hsize_i <= 3'b000;
        hburst_i <= 3'b000;
        htrans_i <= 2'b00;
        hwdata_i <= 32'h0;
        haddr_i <= 32'h0;
        #10 hresetn <= 1'b1;
        #1000 $finish;
    end

    initial begin
        $dumpfile("ahb_sram_tb.vcd");
        $dumpvars(0, ahb_sram_tb.u_ahb_sram);
    end

    initial begin     //“=”如果在时钟有效沿处，数据变化，则会检测到变化后的值
        #50           //“<=”如果在时钟有效沿处，数据变化，则会检测到变化前的值  
        hsel_i <= 1'b1;  
        hwrite_i <= 1'b1;
        hsize_i <= 3'b010;
        hburst_i <= 3'b000; //SINGLE
        htrans_i <= 2'b10; //NONSEQ 
        haddr_i <= 32'h0;       
        repeat (5) begin
            #20
            hwdata_i <= $random;
            haddr_i <= haddr_i + 32'h4;
        end
        haddr_i <= 32'h0;
        hwrite_i <= 1'b0;
        repeat (5) begin
            #20
            haddr_i <= haddr_i + 32'h4;
        end        
    end

    ahb_sram u_ahb_sram(
        .hclk(hclk),
        .sram_clk(sram_clk),
        .hresetn(hresetn),

        .hsel_i(hsel_i),
        .hwrite_i(hwrite_i),
        .hready_i(hready_i),
        .hsize_i(hsize_i),
        .hburst_i(hburst_i),
        .htrans_i(htrans_i),
        .hwdata_i(hwdata_i),
        .haddr_i(haddr_i),

        .hreadyout_o(hreadyout_o),
        .hresp_o(hresp_o),
        .hrdata_o(hrdata_o)
    );


endmodule //ahb_sram_tb

rtl/perip/ahb_sram/ahb_sram_tb.vcd
$date
	Sun Jul 24 21:58:28 2022
$end
$version
	Icarus Verilog
$end
$timescale
	1s
$end
$scope module ahb_sram_tb $end
$scope module u_ahb_sram $end
$var wire 32 ! haddr_i [31:0] $end
$var wire 3 " hburst_i [2:0] $end
$var wire 1 # hclk $end
$var wire 32 $ hrdata_o [31:0] $end
$var wire 1 % hready_i $end
$var wire 1 & hreadyout_o $end
$var wire 1 ' hresetn $end
$var wire 2 ( hresp_o [1:0] $end
$var wire 1 ) hsel_i $end
$var wire 3 * hsize_i [2:0] $end
$var wire 2 + htrans_i [1:0] $end
$var wire 32 , hwdata_i [31:0] $end
$var wire 1 - hwrite_i $end
$var wire 1 . sram_clk $end
$var wire 1 / sram_cs $end
$var wire 1 0 sram_read $end
$var wire 32 1 sram_wdata [31:0] $end
$var wire 1 2 sram_write $end
$var wire 1 3 sram_wen $end
$var wire 32 4 sram_rdata [31:0] $end
$var wire 1 5 sram_bank_sel $end
$var wire 32 6 sram_bank1_rdata [31:0] $end
$var wire 32 7 sram_bank0_rdata [31:0] $end
$var wire 13 8 sram_addr [12:0] $end
$var wire 4 9 bank1_csn [3:0] $end
$var wire 4 : bank0_csn [3:0] $end
$var reg 4 ; bank_csn [3:0] $end
$var reg 32 < haddr_r [31:0] $end
$var reg 3 = hburst_r [2:0] $end
$var reg 3 > hsize_r [2:0] $end
$var reg 2 ? htrans_r [1:0] $end
$var reg 1 @ hwrite_r $end
$scope begin bank0[0] $end
$scope module u_sram_8kx8 $end
$var wire 13 A addr_i [12:0] $end
$var wire 1 B cen_i $end
$var wire 1 . clk $end
$var wire 8 C data_i [7:0] $end
$var wire 1 3 wen_i $end
$var wire 8 D data_o [7:0] $end
$var reg 8 E data_r [7:0] $end
$upscope $end
$upscope $end
$scope begin bank0[1] $end
$scope module u_sram_8kx8 $end
$var wire 13 F addr_i [12:0] $end
$var wire 1 G cen_i $end
$var wire 1 . clk $end
$var wire 8 H data_i [7:0] $end
$var wire 1 3 wen_i $end
$var wire 8 I data_o [7:0] $end
$var reg 8 J data_r [7:0] $end
$upscope $end
$upscope $end
$scope begin bank0[2] $end
$scope module u_sram_8kx8 $end
$var wire 13 K addr_i [12:0] $end
$var wire 1 L cen_i $end
$var wire 1 . clk $end
$var wire 8 M data_i [7:0] $end
$var wire 1 3 wen_i $end
$var wire 8 N data_o [7:0] $end
$var reg 8 O data_r [7:0] $end
$upscope $end
$upscope $end
$scope begin bank0[3] $end
$scope module u_sram_8kx8 $end
$var wire 13 P addr_i [12:0] $end
$var wire 1 Q cen_i $end
$var wire 1 . clk $end
$var wire 8 R data_i [7:0] $end
$var wire 1 3 wen_i $end
$var wire 8 S data_o [7:0] $end
$var reg 8 T data_r [7:0] $end
$upscope $end
$upscope $end
$scope begin bank1[0] $end
$scope module u_sram_8kx8 $end
$var wire 13 U addr_i [12:0] $end
$var wire 1 V cen_i $end
$var wire 1 . clk $end
$var wire 8 W data_i [7:0] $end
$var wire 1 3 wen_i $end
$var wire 8 X data_o [7:0] $end
$var reg 8 Y data_r [7:0] $end
$upscope $end
$upscope $end
$scope begin bank1[1] $end
$scope module u_sram_8kx8 $end
$var wire 13 Z addr_i [12:0] $end
$var wire 1 [ cen_i $end
$var wire 1 . clk $end
$var wire 8 \ data_i [7:0] $end
$var wire 1 3 wen_i $end
$var wire 8 ] data_o [7:0] $end
$var reg 8 ^ data_r [7:0] $end
$upscope $end
$upscope $end
$scope begin bank1[2] $end
$scope module u_sram_8kx8 $end
$var wire 13 _ addr_i [12:0] $end
$var wire 1 ` cen_i $end
$var wire 1 . clk $end
$var wire 8 a data_i [7:0] $end
$var wire 1 3 wen_i $end
$var wire 8 b data_o [7:0] $end
$var reg 8 c data_r [7:0] $end
$upscope $end
$upscope $end
$scope begin bank1[3] $end
$scope module u_sram_8kx8 $end
$var wire 13 d addr_i [12:0] $end
$var wire 1 e cen_i $end
$var wire 1 . clk $end
$var wire 8 f data_i [7:0] $end
$var wire 1 3 wen_i $end
$var wire 8 g data_o [7:0] $end
$var reg 8 h data_r [7:0] $end
$upscope $end
$upscope $end
$upscope $end
$upscope $end
$enddefinitions $end
#0
$dumpvars
bx h
bx g
b0 f
0e
b0 d
bx c
bx b
b0 a
0`
b0 _
bx ^
bx ]
b0 \
0[
b0 Z
bx Y
bx X
b0 W
1V
b0 U
bx T
bx S
b0 R
1Q
b0 P
bx O
bx N
b0 M
1L
b0 K
bx J
bx I
b0 H
1G
b0 F
bx E
bx D
b0 C
1B
b0 A
0@
b0 ?
b0 >
b0 =
b0 <
b1 ;
b1111 :
b1 9
b0 8
bx 7
bx 6
05
bx 4
13
02
b0 1
10
1/
1.
0-
b0 ,
b0 +
b0 *
0)
b0 (
0'
1&
1%
bx $
0#
b0 "
b0 !
$end
#10
1'
0.
1#
#20
1.
0#
#30
0.
1#
#40
1.
0#
#50
b10 +
b10 *
1-
1)
0.
1#
#60
1.
0#
#70
b100100 X
b100100 Y
b110101 ]
b110101 ^
b10101 b
b10101 c
b10010000101010011010100100100 6
b10010 g
b10010 h
0V
b0 9
b0 ;
00
03
12
b100100 C
b110101 H
b10101 M
b10010 R
b100100 W
b110101 \
b10101 a
b10010 f
b10 ?
b10 >
1@
b100 !
b10010000101010011010100100100 1
b10010000101010011010100100100 ,
0.
1#
#80
1.
0#
#90
b10000001 X
b10000001 Y
b1011110 ]
b1011110 ^
b10001001 b
b10001001 c
b11000000100010010101111010000001 6
b11000000 g
b11000000 h
b1 8
b1 A
b1 F
b1 K
b1 P
b1 U
b1 Z
b1 _
b1 d
b0 ;
b10000001 C
b1011110 H
b10001001 M
b11000000 R
b10000001 W
b1011110 \
b10001001 a
b11000000 f
b100 <
b1000 !
b11000000100010010101111010000001 1
b11000000100010010101111010000001 ,
0.
1#
#100
1.
0#
#110
b1001 X
b1001 Y
b11010110 ]
b11010110 ^
b10000100 b
b10000100 c
b10000100100001001101011000001001 6
b10000100 g
b10000100 h
b10 8
b10 A
b10 F
b10 K
b10 P
b10 U
b10 Z
b10 _
b10 d
b0 ;
b1001 C
b11010110 H
b10000100 M
b10000100 R
b1001 W
b11010110 \
b10000100 a
b10000100 f
b1000 <
b1100 !
b10000100100001001101011000001001 1
b10000100100001001101011000001001 ,
0.
1#
#120
1.
0#
#130
b1100011 X
b1100011 Y
b1010110 ]
b1010110 ^
b11110000 b
b11110000 c
b10110001111100000101011001100011 6
b10110001 g
b10110001 h
b11 8
b11 A
b11 F
b11 K
b11 P
b11 U
b11 Z
b11 _
b11 d
b0 ;
b1100011 C
b1010110 H
b11110000 M
b10110001 R
b1100011 W
b1010110 \
b11110000 a
b10110001 f
b1100 <
b10000 !
b10110001111100000101011001100011 1
b10110001111100000101011001100011 ,
0.
1#
#140
1.
0#
#150
b1101 X
b1101 Y
b1111011 ]
b1111011 ^
b10111001 b
b10111001 c
b110101110010111101100001101 6
b110 g
b110 h
b100 8
b100 A
b100 F
b100 K
b100 P
b100 U
b100 Z
b100 _
b100 d
b0 ;
b1101 C
b1111011 H
b10111001 M
b110 R
b1101 W
b1111011 \
b10111001 a
b110 f
b10000 <
0-
b0 !
b110101110010111101100001101 1
b110101110010111101100001101 ,
0.
1#
#160
1.
0#
#170
b100100 X
b100100 Y
b110101 ]
b110101 ^
b10101 b
b10101 c
b10010000101010011010100100100 6
b10010 g
b10010 h
b0 8
b0 A
b0 F
b0 K
b0 P
b0 U
b0 Z
b0 _
b0 d
b0 ;
10
13
02
b0 <
0@
b100 !
0.
1#
#180
1.
0#
#190
b10000001 X
b10000001 Y
b1011110 ]
b1011110 ^
b10001001 b
b10001001 c
b11000000100010010101111010000001 6
b11000000 g
b11000000 h
b1 8
b1 A
b1 F
b1 K
b1 P
b1 U
b1 Z
b1 _
b1 d
b0 ;
b100 <
b1000 !
0.
1#
#200
1.
0#
#210
b1001 X
b1001 Y
b11010110 ]
b11010110 ^
b10000100 b
b10000100 c
b10000100100001001101011000001001 6
b10000100 g
b10000100 h
b10 8
b10 A
b10 F
b10 K
b10 P
b10 U
b10 Z
b10 _
b10 d
b0 ;
b1000 <
b1100 !
0.
1#
#220
1.
0#
#230
b1100011 X
b1100011 Y
b1010110 ]
b1010110 ^
b11110000 b
b11110000 c
b10110001111100000101011001100011 6
b10110001 g
b10110001 h
b11 8
b11 A
b11 F
b11 K
b11 P
b11 U
b11 Z
b11 _
b11 d
b0 ;
b1100 <
b10000 !
0.
1#
#240
1.
0#
#250
b1101 X
b1101 Y
b1111011 ]
b1111011 ^
b10111001 b
b10111001 c
b110101110010111101100001101 6
b110 g
b110 h
b100 8
b100 A
b100 F
b100 K
b100 P
b100 U
b100 Z
b100 _
b100 d
b0 ;
b10000 <
b10100 !
0.
1#
#260
1.
0#
#270
bx X
bx Y
bx ]
bx ^
bx b
bx c
bx 6
bx g
bx h
b101 8
b101 A
b101 F
b101 K
b101 P
b101 U
b101 Z
b101 _
b101 d
b0 ;
b10100 <
0.
1#
