rtl/core/defines.v
//***********************
//全局宏定义
//***********************
`define CPU_CLOCK_HZ        10000000        //cpu时钟10MHz
`define CPU_RESET_ADDR      32'h10000000    //cpu复位地址
`define RST_ENABLE          1'b0            //复位有效
`define RST_DISABLE         1'b1            //复位无效
`define ZERO_WORD           32'h00000000    //32位的数值0
`define WRITE_ENABLE        1'b1            //写使能
`define WRITE_DISABLE       1'b0            //写禁止
`define READ_ENABLE         1'b1            //读使能
`define READ_DISABLE        1'b0            //读禁止
`define EXCP_SYNC_ASSERT    2'b01           //同步异常
`define EXCP_ASYNC_ASSERT_1   2'b10           //异步异常1
`define EXCP_ASYNC_ASSERT_2   2'b11           //异步异常2

//***********************
//IDU信息总线宏定义
//***********************

`define DEC_INST_OP_WIDTH       4                           //DEC指令类型信息宽度
`define DEC_INST_OP             `DEC_INST_OP_WIDTH-1:0      //DEC指令类型信息

//R instruction decode bus
`define DEC_INST_R              `DEC_INST_OP_WIDTH'd1      //R型指令
`define DEC_INST_R_ADD          `DEC_INST_OP_WIDTH         //ADD指令
`define DEC_INST_R_SUB          `DEC_INST_R_ADD+1          
`define DEC_INST_R_SLL          `DEC_INST_R_SUB+1 
`define DEC_INST_R_SLT          `DEC_INST_R_SLL+1 
`define DEC_INST_R_SLTU         `DEC_INST_R_SLT+1 
`define DEC_INST_R_XOR          `DEC_INST_R_SLTU+1
`define DEC_INST_R_SRL          `DEC_INST_R_XOR+1
`define DEC_INST_R_SRA          `DEC_INST_R_SRL+1
`define DEC_INST_R_OR           `DEC_INST_R_SRA+1
`define DEC_INST_R_AND          `DEC_INST_R_OR+1     

`define DEC_R_INFO_BUS_WIDTH    `DEC_INST_R_AND+1           //R型指令译码信息宽度
`define DEC_R_INFO_BUS          `DEC_R_INFO_BUS_WIDTH-1:0   //R型指令译码信息

//I instruction decode bus
`define DEC_INST_I              `DEC_INST_OP_WIDTH'd2      //I型指令
`define DEC_INST_I_ADDI         `DEC_INST_OP_WIDTH         //ADDI指令
`define DEC_INST_I_SLTI         `DEC_INST_I_ADDI+1 
`define DEC_INST_I_SLTIU        `DEC_INST_I_SLTI+1 
`define DEC_INST_I_XORI         `DEC_INST_I_SLTIU+1
`define DEC_INST_I_ORI          `DEC_INST_I_XORI+1
`define DEC_INST_I_ANDI         `DEC_INST_I_ORI+1 
`define DEC_INST_I_SLLI         `DEC_INST_I_ANDI+1  
`define DEC_INST_I_SRLI         `DEC_INST_I_SLLI+1
`define DEC_INST_I_SRAI         `DEC_INST_I_SRLI+1

`define DEC_I_INFO_BUS_WIDTH    `DEC_INST_I_SRAI+1          //I型指令译码信息宽度
`define DEC_I_INFO_BUS          `DEC_I_INFO_BUS_WIDTH-1:0   //I型指令译码信息

//U instruction decode bus
`define DEC_INST_U              `DEC_INST_OP_WIDTH'd3      //U型指令
`define DEC_INST_U_LUI          `DEC_INST_OP_WIDTH         //LUI指令
`define DEC_INST_U_AUIPC        `DEC_INST_U_LUI+1 

`define DEC_U_INFO_BUS_WIDTH    `DEC_INST_U_AUIPC+1         //U型指令译码信息宽度
`define DEC_U_INFO_BUS          `DEC_U_INFO_BUS_WIDTH-1:0   //U型指令译码信息

//L(OAD) instruction decode bus
`define DEC_INST_L              `DEC_INST_OP_WIDTH'd4      //L型指令
`define DEC_INST_L_LB           `DEC_INST_OP_WIDTH         //LB指令
`define DEC_INST_L_LH           `DEC_INST_L_LB+1 
`define DEC_INST_L_LW           `DEC_INST_L_LH+1
`define DEC_INST_L_LBU          `DEC_INST_L_LW+1 
`define DEC_INST_L_LHU          `DEC_INST_L_LBU+1 

`define DEC_L_INFO_BUS_WIDTH    `DEC_INST_L_LHU+1           //L型指令译码信息宽度
`define DEC_L_INFO_BUS          `DEC_L_INFO_BUS_WIDTH-1:0   //L型指令译码信息

//S(TORE) instruction decode bus
`define DEC_INST_S              `DEC_INST_OP_WIDTH'd5      //S型指令
`define DEC_INST_S_SB           `DEC_INST_OP_WIDTH         //SB指令
`define DEC_INST_S_SH           `DEC_INST_S_SB+1 
`define DEC_INST_S_SW           `DEC_INST_S_SH+1

`define DEC_S_INFO_BUS_WIDTH    `DEC_INST_S_SW+1           //S型指令译码信息宽度
`define DEC_S_INFO_BUS          `DEC_S_INFO_BUS_WIDTH-1:0  //S型指令译码信息

//J(UMP) instruction decode bus
`define DEC_INST_J              `DEC_INST_OP_WIDTH'd6      //J型指令
`define DEC_INST_J_JAL          `DEC_INST_OP_WIDTH         //JAL指令
`define DEC_INST_J_JALR         `DEC_INST_J_JAL+1 

`define DEC_J_INFO_BUS_WIDTH    `DEC_INST_J_JALR+1         //J型指令译码信息宽度
`define DEC_J_INFO_BUS          `DEC_J_INFO_BUS_WIDTH-1:0  //J型指令译码信息

//CONTROL STATE REGISTER instruction decode bus
`define DEC_INST_CSR            `DEC_INST_OP_WIDTH'd7       //CSR型指令
`define DEC_INST_CSR_CSRRW      `DEC_INST_OP_WIDTH
`define DEC_INST_CSR_CSRRS      `DEC_INST_CSR_CSRRW+1    
`define DEC_INST_CSR_CSRRC      `DEC_INST_CSR_CSRRS+1
`define DEC_INST_CSR_CSRRWI     `DEC_INST_CSR_CSRRC+1
`define DEC_INST_CSR_CSRRSI     `DEC_INST_CSR_CSRRWI+1
`define DEC_INST_CSR_CSRRCI     `DEC_INST_CSR_CSRRSI+1

`define DEC_CSR_INFO_BUS_WIDTH  `DEC_INST_CSR_CSRRCI+1      //CSR型指令译码信息宽度
`define DEC_CSR_INFO_BUS        `DEC_CSR_INFO_BUS_WIDTH-1:0 //CSR型指令译码信息

//MUL and DIV instruction
`define DEC_INST_MD             `DEC_INST_OP_WIDTH'd8       //MD型指令
`define DEC_INST_MD_MUL         `DEC_INST_OP_WIDTH
`define DEC_INST_MD_MULH        `DEC_INST_MD_MUL+1
`define DEC_INST_MD_MULHSU      `DEC_INST_MD_MULH+1
`define DEC_INST_MD_MULHU       `DEC_INST_MD_MULHSU+1
`define DEC_INST_MD_DIV         `DEC_INST_MD_MULHU+1
`define DEC_INST_MD_DIVU        `DEC_INST_MD_DIV+1
`define DEC_INST_MD_REM         `DEC_INST_MD_DIVU+1
`define DEC_INST_MD_REMU        `DEC_INST_MD_REM+1

`define DEC_MD_INFO_BUS_WIDTH   `DEC_INST_MD_REMU+1        //MD型指令译码信息宽度
`define DEC_MD_INFO_BUS         `DEC_MD_INFO_BUS_WIDTH-1:0 //MD型指令译码信息

//dec info bus
`define DEC_INFO_BUS_WIDTH      `DEC_R_INFO_BUS_WIDTH       //选取最长宽度为DEC信息总线宽度
`define DEC_INFO_BUS            `DEC_INFO_BUS_WIDTH-1:0     //DEC信息总线

//SYSTEM instruction info bus
`define DEC_SYS_BUS_WIDTH       3                           //特权(系统)指令信息总线宽度
`define DEC_SYS_BUS             `DEC_SYS_BUS_WIDTH-1:0      //特权(系统)指令信息总线

`define DEC_SYS_INST_ECALL      0                           //ecall指令
`define DEC_SYS_INST_EBREAK     `DEC_SYS_INST_ECALL+1
`define DEC_SYS_INST_MRET       `DEC_SYS_INST_EBREAK+1

//***********************
//EXE信息总线宏定义
//***********************
`define EXE_INST_OP_WIDTH       2                           //EXE指令类型信息宽度
`define EXE_INST_OP             `EXE_INST_OP_WIDTH-1:0      //EXE指令类型信息

`define EXE_INST_L              `EXE_INST_OP_WIDTH'd1       //L型指令
`define EXE_INST_L_LB           `EXE_INST_OP_WIDTH          //LB指令
`define EXE_INST_L_LH           `EXE_INST_L_LB+1 
`define EXE_INST_L_LW           `EXE_INST_L_LH+1
`define EXE_INST_L_LBU          `EXE_INST_L_LW+1 
`define EXE_INST_L_LHU          `EXE_INST_L_LBU+1 

`define EXE_L_INFO_BUS_WIDTH    `EXE_INST_L_LHU+1           //S型指令信息宽度
`define EXE_L_INFO_BUS          `EXE_L_INFO_BUS_WIDTH-1:0   //S型指令信息

`define EXE_INST_S              `EXE_INST_OP_WIDTH'd2       //S型指令
`define EXE_INST_S_SB           `EXE_INST_OP_WIDTH          //SB指令
`define EXE_INST_S_SH           `EXE_INST_S_SB+1 
`define EXE_INST_S_SW           `EXE_INST_S_SH+1

`define EXE_S_INFO_BUS_WIDTH    `EXE_INST_S_SW+1           //S型指令信息宽度
`define EXE_S_INFO_BUS          `EXE_S_INFO_BUS_WIDTH-1:0   //S型指令信息

`define EXE_INFO_BUS_WIDTH      `EXE_L_INFO_BUS_WIDTH       //选取最长宽度为EXE信息总线宽度
`define EXE_INFO_BUS            `EXE_INFO_BUS_WIDTH-1:0     //EXE信息总线
//***********************
//具体指令的宏定义
//***********************

//***********************
//指令存储器ROM宏定义
//***********************
`define ROM_DEPTH           8192            //指令存储器的深度，单位为word(4字节)
//***********************
//数据存储器ROM宏定义
//***********************
`define MEM_DATA_BUS_WIDTH  `REG_BUS_WIDTH          //数据存储器数据总线宽度
`define MEM_DATA_BUS        `REG_BUS                //数据存储器数据总线
`define MEM_ADDR_BUS_WIDTH  `REG_BUS_WIDTH          //数据存储器地址总线宽度
`define MEM_ADDR_BUS        `MEM_ADDR_BUS_WIDTH-1:0 //数据存储器地址总线
`define RAM_DEPTH           4096                    //数据存储器的深度，单位为word(4字节)

//***********************
//通用寄存器宏定义
//***********************
`define REG_BUS_WIDTH        32                      //regfile数据总线宽度
`define REG_BUS              `REG_BUS_WIDTH-1:0      //regfile数据总线
`define REG_ADDR_BUS_WIDTH   5                       //regfile地址总线宽度
`define REG_ADDR_BUS         `REG_ADDR_BUS_WIDTH-1:0 //regfile地址总线
`define REG_NUM              32                      //regfile数目
`define DOUBLE_REG_BUS_WIDTH 2*`REG_BUS_WIDTH
`define DOUBLE_REG_BUS       `DOUBLE_REG_BUS_WIDTH-1:0   
//***********************
//控制状态寄存器宏定义
//***********************
`define CSR_ADDR_BUS_WIDTH  12                      //csr地址总线宽度
`define CSR_ADDR_BUS        `CSR_ADDR_BUS_WIDTH-1:0 //csr地址总线
// CSR 地址
`define CSR_CYCLE   12'hc00
`define CSR_CYCLEH  12'hc80
`define CSR_MTVEC   12'h305
`define CSR_MCAUSE  12'h342
`define CSR_MEPC    12'h341
`define CSR_MIE     12'h304
`define CSR_MIP     12'h344
`define CSR_MSTATUS 12'h300
`define CSR_MSCRATCH 12'h340

//***********************
//ahb bus 宏定义
//***********************
`define HADDR_BUS_WIDTH `REG_BUS_WIDTH
`define HADDR_BUS       `HADDR_BUS_WIDTH-1:0
`define HDATA_BUS_WIDTH `REG_BUS_WIDTH
`define HDATA_BUS       `HDATA_BUS_WIDTH-1:0

rtl/core/div.v
`include "defines.v"

module div (
    input   wire      clk   ,
    input   wire      rst_n ,

    input   wire                  div_start_i       ,
    input   wire                  div_cancel_i      ,
    input   wire                  div_op1_signed_i  , //被除数符号位信号
    input   wire                  div_op2_signed_i  , //除数符号位信号     
    input   wire    [`REG_BUS]    div_op1_i         , //被除数
    input   wire    [`REG_BUS]    div_op2_i         , //除数

    output  wire                  div_stop_o        ,
    output  wire    [`REG_BUS]    div_res_o         ,
    output  wire    [`REG_BUS]    div_rem_o
);

    reg div_shl;  //右移信号
    always @(posedge clk or negedge rst_n) begin
        if(!rst_n) begin
            div_shl <= 1'b0;
        end else if (div_stop_o || div_cancel_i) begin
            div_shl <= 1'b0;
        end else if (div_start_i) begin
            div_shl <= 1'b1;
        end
    end

    reg [`REG_BUS]  div_op2_r;
    always @(posedge clk or negedge rst_n) begin
        if(!rst_n) begin
            div_op2_r <= `REG_BUS_WIDTH'h0;
        end else if (div_start_i) begin
            div_op2_r <= div_op2_i;
        end
    end

    reg div_op1_signed_r;
    always @(posedge clk or negedge rst_n) begin
        if(!rst_n) begin
            div_op1_signed_r <= 1'b0;
        end else if (div_start_i) begin
            div_op1_signed_r <= div_op1_signed_i;
        end
    end

    reg div_op2_signed_r;
    always @(posedge clk or negedge rst_n) begin
        if(!rst_n) begin
            div_op2_signed_r <= 1'b0;
        end else if (div_start_i) begin
            div_op2_signed_r <= div_op2_signed_i;
        end
    end

    reg [5:0]   count;
    always @(posedge clk or negedge rst_n) begin
        if(!rst_n) begin
            count <= 6'b000000;
        end else if (div_shl && !div_stop_o && !div_cancel_i) begin
            count <= count + 1'b1;
        end else if (div_start_i) begin
            if ((|div_op2_i) == 1'b0) begin
                count <= 6'b100000;
            end else begin
                count <= 6'b000000;
            end
        end else begin
            count <= 6'b000000;
        end
    end    

    reg [`DOUBLE_REG_BUS]   div_res_rem;

    wire    [`REG_BUS]  sub_op1 = div_res_rem[`DOUBLE_REG_BUS_WIDTH-2:`REG_BUS_WIDTH-1];
    wire    [`REG_BUS]  sub_op2 = div_op2_r;    
    wire    [`REG_BUS]  sub_res = sub_op1 - sub_op2;
    wire    [`REG_BUS]  sub_nxt = sub_res[`REG_BUS_WIDTH-1] ? sub_op1 : sub_res;

    always @(posedge clk or negedge rst_n) begin
        if(!rst_n) begin
            div_res_rem <= `DOUBLE_REG_BUS_WIDTH'h0;
        end else if (div_shl && !div_stop_o && !div_cancel_i) begin
            div_res_rem <= {sub_nxt, div_res_rem[`REG_BUS_WIDTH-2:0], !sub_res[`REG_BUS_WIDTH-1]};
        end else if (div_cancel_i) begin
            div_res_rem <= `DOUBLE_REG_BUS_WIDTH'h0;
        end else if (div_start_i) begin
            if (|div_op2_i == 1'b0) begin
                div_res_rem <= `DOUBLE_REG_BUS_WIDTH'h0;
            end else begin
                div_res_rem <= {`REG_BUS_WIDTH'h0, div_op1_i};
            end
        end
    end

    assign div_res_o = ((div_op1_signed_r ^ div_op2_signed_r) && (!(|div_op2_i == 1'b0))) ? 
        ~div_res_rem[`REG_BUS_WIDTH-1:0] + 1'b1 : div_res_rem[`REG_BUS_WIDTH-1:0];
    assign div_rem_o = (div_op1_signed_r && (!(|div_op2_i == 1'b0))) ? 
        ~div_res_rem[`DOUBLE_REG_BUS_WIDTH-1:`REG_BUS_WIDTH] + 1'b1 : div_res_rem[`DOUBLE_REG_BUS_WIDTH-1:`REG_BUS_WIDTH];

    assign div_stop_o = (count[5] == 1'b1) && div_shl;    

endmodule //div

rtl/core/div_tb.v
`include "defines.v"

module div_tb ();

    reg clk;
    reg rst_n;

    reg                         div_start_i;
    reg                         div_cancel_i;
    reg                         div_op1_signed_i;
    reg                         div_op2_signed_i;        
    reg     [`REG_BUS]          div_op1_i;
    reg     [`REG_BUS]          div_op2_i;    

    wire                        div_stop_o;
    wire    [`REG_BUS]          div_res_o;          
    wire    [`REG_BUS]          div_rem_o;

    div u_div(
        .clk(clk),
        .rst_n(rst_n),
        .div_start_i(div_start_i),
        .div_cancel_i(div_cancel_i),
        .div_op1_signed_i(div_op1_signed_i),
        .div_op2_signed_i(div_op2_signed_i),
        .div_op1_i(div_op1_i),
        .div_op2_i(div_op2_i),
        .div_stop_o(div_stop_o),
        .div_res_o(div_res_o),
        .div_rem_o(div_rem_o)
    );

    always #10 clk = ~clk;

    initial begin
        clk = 1'b0;
        rst_n = 1'b0;
        div_start_i = 1'b0;
        div_cancel_i = 1'b0;
        div_op1_signed_i = 1'b0;
        div_op2_signed_i = 1'b0;
        div_op1_i = 32'd0;
        div_op2_i = 32'd0;
        #100 rst_n = 1'b1;
        #3000 $finish;
    end

    integer i;
    initial begin
        i = 0;
        repeat (3) begin
            #200
            div_start_i <= 1'b1;
            div_op1_signed_i <= ~div_op1_signed_i;
            div_op2_signed_i <= div_op2_signed_i;
            div_op1_i <= div_op1_i + i*32'd10;
            div_op2_i <= div_op2_i + i*32'd3;
            @ (posedge div_stop_o);
            div_start_i <= 1'b0;
            i <= i+1;
        end
    end

    initial begin
        $dumpfile("div_tb.vcd");
        $dumpvars(0, div_tb.u_div);
    end

endmodule //div_tb

rtl/core/div_tb.vcd
$date
	Wed Jun 15 14:50:55 2022
$end
$version
	Icarus Verilog
$end
$timescale
	1s
$end
$scope module div_tb $end
$scope module u_div $end
$var wire 1 ! clk $end
$var wire 1 " div_cancel_i $end
$var wire 32 # div_op1_i [31:0] $end
$var wire 1 $ div_op1_signed_i $end
$var wire 32 % div_op2_i [31:0] $end
$var wire 1 & div_op2_signed_i $end
$var wire 1 ' div_start_i $end
$var wire 1 ( div_stop_o $end
$var wire 1 ) rst_n $end
$var wire 32 * sub_op2 [31:0] $end
$var wire 32 + sub_res [31:0] $end
$var wire 32 , sub_op1 [31:0] $end
$var wire 32 - sub_nxt [31:0] $end
$var wire 32 . div_res_o [31:0] $end
$var wire 32 / div_rem_o [31:0] $end
$var reg 6 0 count [5:0] $end
$var reg 1 1 div_op1_signed_r $end
$var reg 32 2 div_op2_r [31:0] $end
$var reg 1 3 div_op2_signed_r $end
$var reg 64 4 div_res_rem [63:0] $end
$var reg 1 5 div_shl $end
$upscope $end
$upscope $end
$enddefinitions $end
#0
$dumpvars
05
b0 4
03
b0 2
01
b0 0
b0 /
b0 .
b0 -
b0 ,
b0 +
b0 *
0)
0(
0'
0&
b0 %
0$
b0 #
0"
0!
$end
#10
1!
#20
0!
#30
1!
#40
0!
#50
1!
#60
0!
#70
1!
#80
0!
#90
1!
#100
0!
1)
#110
1!
#120
0!
#130
1!
#140
0!
#150
1!
#160
0!
#170
1!
#180
0!
#190
1!
#200
1$
1'
0!
#210
0'
1(
b100000 0
11
15
1!
#220
0!
#230
0(
05
b0 0
1!
#240
0!
#250
1!
#260
0!
#270
1!
#280
0!
#290
1!
#300
0!
#310
1!
#320
0!
#330
1!
#340
0!
#350
1!
#360
0!
#370
1!
#380
0!
#390
1!
#400
0!
#410
b11 %
b1010 #
0$
1'
1!
#420
0!
#430
b1010 .
b0 -
15
b11111111111111111111111111111101 +
b11 *
b11 2
01
b1010 4
1!
#440
0!
#450
b10100 .
b10100 4
b1 0
1!
#460
0!
#470
b101000 .
b10 0
b101000 4
1!
#480
0!
#490
b1010000 .
b1010000 4
b11 0
1!
#500
0!
#510
b10100000 .
b100 0
b10100000 4
1!
#520
0!
#530
b101000000 .
b101000000 4
b101 0
1!
#540
0!
#550
b1010000000 .
b110 0
b1010000000 4
1!
#560
0!
#570
b10100000000 .
b10100000000 4
b111 0
1!
#580
0!
#590
b101000000000 .
b1000 0
b101000000000 4
1!
#600
0!
#610
b1010000000000 .
b1010000000000 4
b1001 0
1!
#620
0!
#630
b10100000000000 .
b1010 0
b10100000000000 4
1!
#640
0!
#650
b101000000000000 .
b101000000000000 4
b1011 0
1!
#660
0!
#670
b1010000000000000 .
b1100 0
b1010000000000000 4
1!
#680
0!
#690
b10100000000000000 .
b10100000000000000 4
b1101 0
1!
#700
0!
#710
b101000000000000000 .
b1110 0
b101000000000000000 4
1!
#720
0!
#730
b1010000000000000000 .
b1010000000000000000 4
b1111 0
1!
#740
0!
#750
b10100000000000000000 .
b10000 0
b10100000000000000000 4
1!
#760
0!
#770
b101000000000000000000 .
b101000000000000000000 4
b10001 0
1!
#780
0!
#790
b1010000000000000000000 .
b10010 0
b1010000000000000000000 4
1!
#800
0!
#810
b10100000000000000000000 .
b10100000000000000000000 4
b10011 0
1!
#820
0!
#830
b101000000000000000000000 .
b10100 0
b101000000000000000000000 4
1!
#840
0!
#850
b1010000000000000000000000 .
b1010000000000000000000000 4
b10101 0
1!
#860
0!
#870
b10100000000000000000000000 .
b10110 0
b10100000000000000000000000 4
1!
#880
0!
#890
b101000000000000000000000000 .
b101000000000000000000000000 4
b10111 0
1!
#900
0!
#910
b1010000000000000000000000000 .
b11000 0
b1010000000000000000000000000 4
1!
#920
0!
#930
b10100000000000000000000000000 .
b10100000000000000000000000000 4
b11001 0
1!
#940
0!
#950
b101000000000000000000000000000 .
b11010 0
b101000000000000000000000000000 4
1!
#960
0!
#970
b1010000000000000000000000000000 .
b1010000000000000000000000000000 4
b11011 0
1!
#980
0!
#990
b1 -
b10100000000000000000000000000000 .
b11111111111111111111111111111110 +
b1 ,
b11100 0
b10100000000000000000000000000000 4
1!
#1000
0!
#1010
b10 -
b1000000000000000000000000000000 .
b1 /
b11111111111111111111111111111111 +
b10 ,
b101000000000000000000000000000000 4
b11101 0
1!
#1020
0!
#1030
b10 -
b10000000000000000000000000000000 .
b10 /
b10 +
b101 ,
b11110 0
b1010000000000000000000000000000000 4
1!
#1040
0!
#1050
b1 -
b1 .
b1 +
b100 ,
b1000000000000000000000000000000001 4
b11111 0
1!
#1060
0!
#1070
0'
1(
b10 -
b11 .
b1 /
b11111111111111111111111111111111 +
b10 ,
b100000 0
b100000000000000000000000000000011 4
1!
#1080
0!
#1090
0(
b0 0
05
1!
#1100
0!
#1110
1!
#1120
0!
#1130
1!
#1140
0!
#1150
1!
#1160
0!
#1170
1!
#1180
0!
#1190
1!
#1200
0!
#1210
1!
#1220
0!
#1230
1!
#1240
0!
#1250
1!
#1260
0!
#1270
b1001 %
b11110 #
1$
1'
1!
#1280
0!
#1290
b0 -
b11111111111111111111111111100010 .
b0 /
b0 ,
b11110 4
11
b11111111111111111111111111110111 +
b1001 *
b1001 2
15
1!
#1300
0!
#1310
b11111111111111111111111111000100 .
b1 0
b111100 4
1!
#1320
0!
#1330
b11111111111111111111111110001000 .
b1111000 4
b10 0
1!
#1340
0!
#1350
b11111111111111111111111100010000 .
b11 0
b11110000 4
1!
#1360
0!
#1370
b11111111111111111111111000100000 .
b111100000 4
b100 0
1!
#1380
0!
#1390
b11111111111111111111110001000000 .
b101 0
b1111000000 4
1!
#1400
0!
#1410
b11111111111111111111100010000000 .
b11110000000 4
b110 0
1!
#1420
0!
#1430
b11111111111111111111000100000000 .
b111 0
b111100000000 4
1!
#1440
0!
#1450
b11111111111111111110001000000000 .
b1111000000000 4
b1000 0
1!
#1460
0!
#1470
b11111111111111111100010000000000 .
b1001 0
b11110000000000 4
1!
#1480
0!
#1490
b11111111111111111000100000000000 .
b111100000000000 4
b1010 0
1!
#1500
0!
#1510
b11111111111111110001000000000000 .
b1011 0
b1111000000000000 4
1!
#1520
0!
#1530
b11111111111111100010000000000000 .
b11110000000000000 4
b1100 0
1!
#1540
0!
#1550
b11111111111111000100000000000000 .
b1101 0
b111100000000000000 4
1!
#1560
0!
#1570
b11111111111110001000000000000000 .
b1111000000000000000 4
b1110 0
1!
#1580
0!
#1590
b11111111111100010000000000000000 .
b1111 0
b11110000000000000000 4
1!
#1600
0!
#1610
b11111111111000100000000000000000 .
b111100000000000000000 4
b10000 0
1!
#1620
0!
#1630
b11111111110001000000000000000000 .
b10001 0
b1111000000000000000000 4
1!
#1640
0!
#1650
b11111111100010000000000000000000 .
b11110000000000000000000 4
b10010 0
1!
#1660
0!
#1670
b11111111000100000000000000000000 .
b10011 0
b111100000000000000000000 4
1!
#1680
0!
#1690
b11111110001000000000000000000000 .
b1111000000000000000000000 4
b10100 0
1!
#1700
0!
#1710
b11111100010000000000000000000000 .
b10101 0
b11110000000000000000000000 4
1!
#1720
0!
#1730
b11111000100000000000000000000000 .
b111100000000000000000000000 4
b10110 0
1!
#1740
0!
#1750
b11110001000000000000000000000000 .
b10111 0
b1111000000000000000000000000 4
1!
#1760
0!
#1770
b11100010000000000000000000000000 .
b11110000000000000000000000000 4
b11000 0
1!
#1780
0!
#1790
b11000100000000000000000000000000 .
b11001 0
b111100000000000000000000000000 4
1!
#1800
0!
#1810
b10001000000000000000000000000000 .
b1111000000000000000000000000000 4
b11010 0
1!
#1820
0!
#1830
b10000000000000000000000000000 .
b1 -
b11111111111111111111111111111000 +
b1 ,
b11011 0
b11110000000000000000000000000000 4
1!
#1840
0!
#1850
b100000000000000000000000000000 .
b11111111111111111111111111111111 /
b11 -
b11111111111111111111111111111010 +
b11 ,
b111100000000000000000000000000000 4
b11100 0
1!
#1860
0!
#1870
b1000000000000000000000000000000 .
b11111111111111111111111111111101 /
b111 -
b11111111111111111111111111111110 +
b111 ,
b11101 0
b1111000000000000000000000000000000 4
1!
#1880
0!
#1890
b10000000000000000000000000000000 .
b11111111111111111111111111111001 /
b110 -
b110 +
b1111 ,
b11110000000000000000000000000000000 4
b11110 0
1!
#1900
0!
#1910
b11111111111111111111111111111111 .
b11111111111111111111111111111010 /
b11 -
b11 +
b1100 ,
b11111 0
b11000000000000000000000000000000001 4
1!
#1920
0!
#1930
0'
b11111111111111111111111111111101 .
b11111111111111111111111111111101 /
1(
b110 -
b11111111111111111111111111111101 +
b110 ,
b1100000000000000000000000000000011 4
b100000 0
1!
#1940
0!
#1950
0(
05
b0 0
1!
